MANIFEST.in
README.rst
setup.py
aliyun_python_sdk_hsm.egg-info/PKG-INFO
aliyun_python_sdk_hsm.egg-info/SOURCES.txt
aliyun_python_sdk_hsm.egg-info/dependency_links.txt
aliyun_python_sdk_hsm.egg-info/requires.txt
aliyun_python_sdk_hsm.egg-info/top_level.txt
aliyunsdkhsm/__init__.py
aliyunsdkhsm/request/__init__.py
aliyunsdkhsm/request/v20180111/ConfigNetworkRequest.py
aliyunsdkhsm/request/v20180111/ConfigWhiteListRequest.py
aliyunsdkhsm/request/v20180111/CreateInstanceRequest.py
aliyunsdkhsm/request/v20180111/DescribeInstancesRequest.py
aliyunsdkhsm/request/v20180111/DescribeRegionsRequest.py
aliyunsdkhsm/request/v20180111/ModifyInstanceRequest.py
aliyunsdkhsm/request/v20180111/ReleaseInstanceRequest.py
aliyunsdkhsm/request/v20180111/RenewInstanceRequest.py
aliyunsdkhsm/request/v20180111/__init__.py